codecutter/__init__.py
codecutter/astwalk.py
codecutter/modifiers.py
codecutter-0.2.0.dist-info/METADATA
codecutter-0.2.0.dist-info/WHEEL
codecutter-0.2.0.dist-info/RECORD
