Metadata-Version: 2.1
Name: codecutter
Version: 0.2.0
Summary: Library for function preprocessing and optimization
Home-page: https://github.com/b10011/codecutter
Keywords: preprocess,preprocessing,preprocessor,optimize,optimizer
Author: Niko Järvinen
Author-email: nbjarvinen@gmail.com
Requires-Python: >=3.8,<4.0
Classifier: Intended Audience :: Developers
Classifier: License :: OSI Approved :: MIT License
Classifier: Programming Language :: Python :: 3
Classifier: Programming Language :: Python :: 3.8
Classifier: Programming Language :: Python :: 3.9
Classifier: Programming Language :: Python :: 3.10
Classifier: Programming Language :: Python :: 3.11
Classifier: Programming Language :: Python :: 3.12
Classifier: Programming Language :: Python :: 3.13
Classifier: Topic :: Software Development :: Libraries
Project-URL: Documentation, https://github.com/b10011/codecutter/blob/master/documentation.md
Project-URL: Repository, https://github.com/b10011/codecutter
